algoinc/__init__.py
algoinc/__main__.py
algoinc/cli.py
algoinc/fetcher.py
algoinc/algorithms/__init__.py
algoinc/algorithms/bubble_sort.c
algoinc/algorithms/merge_sort.c
algoinc/algorithms/quick_sort.c
algoinc-0.2.0.dist-info/METADATA
algoinc-0.2.0.dist-info/WHEEL
algoinc-0.2.0.dist-info/entry_points.txt
algoinc-0.2.0.dist-info/top_level.txt
algoinc-0.2.0.dist-info/RECORD
